busby
