Metadata-Version: 1.0
Name: busby
Version: 0.11
Summary: Parse a csv file and send through a websocket.
Home-page: https://github.com/yhat/busby
Author: Jessie Frazelle
Author-email: jessie@yhathq.com
License: BSD
Platform: UNKNOWN
